tests/__init__.py
tests/test_auth.py
web3login/__init__.py
web3login/auth.py
web3login/cli.py
web3login/exceptions.py
web3login/py.typed
web3login/version.py
web3login/middlewares/__init__.py
web3login/middlewares/fastapi.py
web3login-0.0.5.dist-info/METADATA
web3login-0.0.5.dist-info/WHEEL
web3login-0.0.5.dist-info/entry_points.txt
web3login-0.0.5.dist-info/top_level.txt
web3login-0.0.5.dist-info/RECORD
