Metadata-Version: 2.1
Name: web3login
Version: 0.0.5
Summary: Moonstream: Open source Web3 authorization library
Home-page: https://github.com/bugout-dev/web3login
Author: Moonstream
Author-email: engineering@moonstream.to
License: UNKNOWN
Platform: UNKNOWN
Classifier: Development Status :: 3 - Alpha
Classifier: Programming Language :: Python
Classifier: License :: OSI Approved :: Apache Software License
Classifier: Topic :: Software Development :: Libraries
Requires-Python: >=3.8
Requires-Dist: eip712 (==0.1.0)
Requires-Dist: eth-typing (>=2.3.0)
Requires-Dist: web3 (>=5.30.0)
Provides-Extra: dev
Requires-Dist: black ; extra == 'dev'
Requires-Dist: mypy ; extra == 'dev'
Requires-Dist: isort ; extra == 'dev'
Provides-Extra: distribute
Requires-Dist: setuptools ; extra == 'distribute'
Requires-Dist: twine ; extra == 'distribute'
Requires-Dist: wheel ; extra == 'distribute'
Provides-Extra: fastapi
Requires-Dist: fastapi ; extra == 'fastapi'
